jinja_subrender/__init__.py
jinja_subrender-0.0.1.dist-info/METADATA
jinja_subrender-0.0.1.dist-info/WHEEL
jinja_subrender-0.0.1.dist-info/top_level.txt
jinja_subrender-0.0.1.dist-info/RECORD
