Metadata-Version: 2.1
Name: jinja-subrender
Version: 0.0.1
Summary: A simple way to render a Jinja2 template within another Jinja2 template.
Home-page: https://github.com/GrantGMiller/jinja_subrender
Author: Grant miller
Author-email: grant@grant-miller.com
License: PSF
Project-URL: Source Code, https://github.com/GrantGMiller/jinja_subrender
Keywords: grant miller flask jinja template render within subrender
Platform: UNKNOWN
Requires-Dist: flask
